docs/conf.py
src/__init__.py
src/client.py
src/connected_vehicle_client.py
src/errors.py
src/types.py
src/api/__init__.py
src/api/climate/__init__.py
src/api/climate/get_environment_vals.py
src/api/climate/invoke_climatization_start.py
src/api/climate/invoke_climatization_stop.py
src/api/commands/__init__.py
src/api/commands/get_command_list.py
src/api/commands/get_commands_accessibility.py
src/api/diagnostics/__init__.py
src/api/diagnostics/get_brake_status.py
src/api/diagnostics/get_diagnostics.py
src/api/diagnostics/get_engine_diagnostics.py
src/api/doors_windows_and_locks/__init__.py
src/api/doors_windows_and_locks/get_door_and_lock_status.py
src/api/doors_windows_and_locks/get_window_status.py
src/api/doors_windows_and_locks/invoke_lock.py
src/api/doors_windows_and_locks/invoke_lock_reduced_guard.py
src/api/doors_windows_and_locks/invoke_unlock.py
src/api/engine/__init__.py
src/api/engine/get_engine_status.py
src/api/engine/invoke_engine_start.py
src/api/engine/invoke_engine_stop.py
src/api/fuel/__init__.py
src/api/fuel/get_fuel_amount.py
src/api/fuel/getbatterychargelevel.py
src/api/lights_and_sound/__init__.py
src/api/lights_and_sound/invoke_flash.py
src/api/lights_and_sound/invoke_honk.py
src/api/lights_and_sound/invoke_honk_flash.py
src/api/odometer/__init__.py
src/api/odometer/get_odometer.py
src/api/statistics/__init__.py
src/api/statistics/get_statistics.py
src/api/tyres/__init__.py
src/api/tyres/get_tyre_pressure_values.py
src/api/vehicle/__init__.py
src/api/vehicle/get_vehicle_details.py
src/api/vehicle/get_vehicle_list.py
src/api/warnings/__init__.py
src/api/warnings/get_warnings.py
src/models/__init__.py
src/models/battery_charge.py
src/models/battery_charge_level_response.py
src/models/brake_status.py
src/models/brake_status_response.py
src/models/command_accessibility.py
src/models/command_accessibility_response.py
src/models/command_list_item.py
src/models/command_list_item_command.py
src/models/command_list_response.py
connected_vehicle_client-2.0.1.dist-info/METADATA
connected_vehicle_client-2.0.1.dist-info/WHEEL
connected_vehicle_client-2.0.1.dist-info/licenses/LICENSE
connected_vehicle_client-2.0.1.dist-info/RECORD
