Metadata-Version: 2.1
Name: connected-vehicle-client
Version: 2.0.1
Summary: A client library for accessing Connected Vehicle
Project-URL: Homepage, https://github.com/exbachi/volvo_connected_vehicle
Project-URL: Bug Tracker, https://github.com/exbachi/volvo_connected_vehicle/issues
Author-email: exbachi <marco.sauter@gmx.de>
Maintainer-email: exbachi <marco.sauter@gmx.de>
License-Expression: MIT
License-File: LICENSE
Classifier: License :: OSI Approved :: MIT License
Classifier: Operating System :: OS Independent
Classifier: Programming Language :: Python :: 3
Requires-Python: >=3.8
Requires-Dist: attrs==22.2.0,>=21.3.0
Requires-Dist: httpx<0.25.0,>=0.15.4
Requires-Dist: python-dateutil>=2.8.0
